streamlit_back_camera_input/__init__.py
streamlit_back_camera_input/frontend/index.html
streamlit_back_camera_input/frontend/main.js
streamlit_back_camera_input/frontend/streamlit-component-lib.js
streamlit_back_camera_input/frontend/style.css
streamlit_back_camera_input-0.1.1.dist-info/LICENSE
streamlit_back_camera_input-0.1.1.dist-info/METADATA
streamlit_back_camera_input-0.1.1.dist-info/WHEEL
streamlit_back_camera_input-0.1.1.dist-info/top_level.txt
streamlit_back_camera_input-0.1.1.dist-info/RECORD
